<annotation>
        <folder>FOLDER</folder>
        <filename>024801509.jpg</filename>
        <path>data/scenes/train2\024801509.jpg</path>
        <source>
                <database>Unknown</database>
        </source>
        <size>
                <width>720</width>
                <height>720</height>
                <depth>3</depth>
        </size>
 <object>
                <name>8c</name>
                <pose>Unspecified</pose>
                <truncated>0</truncated>
                <difficult>0</difficult>
                <bndbox>
                        <xmin>286</xmin>
                        <ymin>479</ymin>
                        <xmax>333</xmax>
                        <ymax>559</ymax>
                </bndbox>
        </object>
 <object>
                <name>6s</name>
                <pose>Unspecified</pose>
                <truncated>0</truncated>
                <difficult>0</difficult>
                <bndbox>
                        <xmin>250</xmin>
                        <ymin>470</ymin>
                        <xmax>283</xmax>
                        <ymax>558</ymax>
                </bndbox>
        </object>
 <object>
                <name>8s</name>
                <pose>Unspecified</pose>
                <truncated>0</truncated>
                <difficult>0</difficult>
                <bndbox>
                        <xmin>193</xmin>
                        <ymin>469</ymin>
                        <xmax>237</xmax>
                        <ymax>546</ymax>
                </bndbox>
        </object>
 <object>
                <name>8s</name>
                <pose>Unspecified</pose>
                <truncated>0</truncated>
                <difficult>0</difficult>
                <bndbox>
                        <xmin>111</xmin>
                        <ymin>304</ymin>
                        <xmax>156</xmax>
                        <ymax>384</ymax>
                </bndbox>
        </object>
</annotation>        
