<annotation>
        <folder>FOLDER</folder>
        <filename>102149755.jpg</filename>
        <path>data/scenes/train2\102149755.jpg</path>
        <source>
                <database>Unknown</database>
        </source>
        <size>
                <width>720</width>
                <height>720</height>
                <depth>3</depth>
        </size>
 <object>
                <name>9d</name>
                <pose>Unspecified</pose>
                <truncated>0</truncated>
                <difficult>0</difficult>
                <bndbox>
                        <xmin>307</xmin>
                        <ymin>328</ymin>
                        <xmax>383</xmax>
                        <ymax>392</ymax>
                </bndbox>
        </object>
 <object>
                <name>2d</name>
                <pose>Unspecified</pose>
                <truncated>0</truncated>
                <difficult>0</difficult>
                <bndbox>
                        <xmin>336</xmin>
                        <ymin>299</ymin>
                        <xmax>400</xmax>
                        <ymax>368</ymax>
                </bndbox>
        </object>
 <object>
                <name>7c</name>
                <pose>Unspecified</pose>
                <truncated>0</truncated>
                <difficult>0</difficult>
                <bndbox>
                        <xmin>386</xmin>
                        <ymin>269</ymin>
                        <xmax>447</xmax>
                        <ymax>349</ymax>
                </bndbox>
        </object>
 <object>
                <name>7c</name>
                <pose>Unspecified</pose>
                <truncated>0</truncated>
                <difficult>0</difficult>
                <bndbox>
                        <xmin>563</xmin>
                        <ymin>328</ymin>
                        <xmax>625</xmax>
                        <ymax>409</ymax>
                </bndbox>
        </object>
</annotation>        
