<annotation>
        <folder>FOLDER</folder>
        <filename>263169092.jpg</filename>
        <path>data/scenes/train2\263169092.jpg</path>
        <source>
                <database>Unknown</database>
        </source>
        <size>
                <width>720</width>
                <height>720</height>
                <depth>3</depth>
        </size>
 <object>
                <name>9d</name>
                <pose>Unspecified</pose>
                <truncated>0</truncated>
                <difficult>0</difficult>
                <bndbox>
                        <xmin>522</xmin>
                        <ymin>277</ymin>
                        <xmax>608</xmax>
                        <ymax>395</ymax>
                </bndbox>
        </object>
 <object>
                <name>9d</name>
                <pose>Unspecified</pose>
                <truncated>0</truncated>
                <difficult>0</difficult>
                <bndbox>
                        <xmin>239</xmin>
                        <ymin>211</ymin>
                        <xmax>332</xmax>
                        <ymax>328</ymax>
                </bndbox>
        </object>
 <object>
                <name>9c</name>
                <pose>Unspecified</pose>
                <truncated>0</truncated>
                <difficult>0</difficult>
                <bndbox>
                        <xmin>311</xmin>
                        <ymin>396</ymin>
                        <xmax>432</xmax>
                        <ymax>474</ymax>
                </bndbox>
        </object>
 <object>
                <name>9c</name>
                <pose>Unspecified</pose>
                <truncated>0</truncated>
                <difficult>0</difficult>
                <bndbox>
                        <xmin>53</xmin>
                        <ymin>500</ymin>
                        <xmax>164</xmax>
                        <ymax>576</ymax>
                </bndbox>
        </object>
</annotation>        
