<annotation>
        <folder>FOLDER</folder>
        <filename>293344265.jpg</filename>
        <path>data/scenes/train2\293344265.jpg</path>
        <source>
                <database>Unknown</database>
        </source>
        <size>
                <width>720</width>
                <height>720</height>
                <depth>3</depth>
        </size>
 <object>
                <name>5d</name>
                <pose>Unspecified</pose>
                <truncated>0</truncated>
                <difficult>0</difficult>
                <bndbox>
                        <xmin>187</xmin>
                        <ymin>227</ymin>
                        <xmax>221</xmax>
                        <ymax>315</ymax>
                </bndbox>
        </object>
 <object>
                <name>5d</name>
                <pose>Unspecified</pose>
                <truncated>0</truncated>
                <difficult>0</difficult>
                <bndbox>
                        <xmin>303</xmin>
                        <ymin>366</ymin>
                        <xmax>338</xmax>
                        <ymax>445</ymax>
                </bndbox>
        </object>
 <object>
                <name>7h</name>
                <pose>Unspecified</pose>
                <truncated>0</truncated>
                <difficult>0</difficult>
                <bndbox>
                        <xmin>435</xmin>
                        <ymin>227</ymin>
                        <xmax>513</xmax>
                        <ymax>285</ymax>
                </bndbox>
        </object>
 <object>
                <name>7h</name>
                <pose>Unspecified</pose>
                <truncated>0</truncated>
                <difficult>0</difficult>
                <bndbox>
                        <xmin>380</xmin>
                        <ymin>411</ymin>
                        <xmax>457</xmax>
                        <ymax>468</ymax>
                </bndbox>
        </object>
</annotation>        
