<annotation>
        <folder>FOLDER</folder>
        <filename>303439807.jpg</filename>
        <path>data/scenes/train2\303439807.jpg</path>
        <source>
                <database>Unknown</database>
        </source>
        <size>
                <width>720</width>
                <height>720</height>
                <depth>3</depth>
        </size>
 <object>
                <name>2c</name>
                <pose>Unspecified</pose>
                <truncated>0</truncated>
                <difficult>0</difficult>
                <bndbox>
                        <xmin>338</xmin>
                        <ymin>280</ymin>
                        <xmax>406</xmax>
                        <ymax>348</ymax>
                </bndbox>
        </object>
 <object>
                <name>3d</name>
                <pose>Unspecified</pose>
                <truncated>0</truncated>
                <difficult>0</difficult>
                <bndbox>
                        <xmin>306</xmin>
                        <ymin>294</ymin>
                        <xmax>372</xmax>
                        <ymax>379</ymax>
                </bndbox>
        </object>
 <object>
                <name>9d</name>
                <pose>Unspecified</pose>
                <truncated>0</truncated>
                <difficult>0</difficult>
                <bndbox>
                        <xmin>257</xmin>
                        <ymin>316</ymin>
                        <xmax>303</xmax>
                        <ymax>395</ymax>
                </bndbox>
        </object>
 <object>
                <name>9d</name>
                <pose>Unspecified</pose>
                <truncated>0</truncated>
                <difficult>0</difficult>
                <bndbox>
                        <xmin>103</xmin>
                        <ymin>214</ymin>
                        <xmax>149</xmax>
                        <ymax>293</ymax>
                </bndbox>
        </object>
</annotation>        
