<annotation>
        <folder>FOLDER</folder>
        <filename>441496172.jpg</filename>
        <path>data/scenes/train2\441496172.jpg</path>
        <source>
                <database>Unknown</database>
        </source>
        <size>
                <width>720</width>
                <height>720</height>
                <depth>3</depth>
        </size>
 <object>
                <name>5c</name>
                <pose>Unspecified</pose>
                <truncated>0</truncated>
                <difficult>0</difficult>
                <bndbox>
                        <xmin>385</xmin>
                        <ymin>326</ymin>
                        <xmax>468</xmax>
                        <ymax>370</ymax>
                </bndbox>
        </object>
 <object>
                <name>Ac</name>
                <pose>Unspecified</pose>
                <truncated>0</truncated>
                <difficult>0</difficult>
                <bndbox>
                        <xmin>380</xmin>
                        <ymin>373</ymin>
                        <xmax>462</xmax>
                        <ymax>412</ymax>
                </bndbox>
        </object>
 <object>
                <name>Jd</name>
                <pose>Unspecified</pose>
                <truncated>0</truncated>
                <difficult>0</difficult>
                <bndbox>
                        <xmin>366</xmin>
                        <ymin>416</ymin>
                        <xmax>454</xmax>
                        <ymax>465</ymax>
                </bndbox>
        </object>
 <object>
                <name>Jd</name>
                <pose>Unspecified</pose>
                <truncated>0</truncated>
                <difficult>0</difficult>
                <bndbox>
                        <xmin>208</xmin>
                        <ymin>502</ymin>
                        <xmax>293</xmax>
                        <ymax>549</ymax>
                </bndbox>
        </object>
</annotation>        
