<annotation>
        <folder>FOLDER</folder>
        <filename>883343805.jpg</filename>
        <path>data/scenes/train2\883343805.jpg</path>
        <source>
                <database>Unknown</database>
        </source>
        <size>
                <width>720</width>
                <height>720</height>
                <depth>3</depth>
        </size>
 <object>
                <name>Qs</name>
                <pose>Unspecified</pose>
                <truncated>0</truncated>
                <difficult>0</difficult>
                <bndbox>
                        <xmin>200</xmin>
                        <ymin>547</ymin>
                        <xmax>275</xmax>
                        <ymax>596</ymax>
                </bndbox>
        </object>
 <object>
                <name>8s</name>
                <pose>Unspecified</pose>
                <truncated>0</truncated>
                <difficult>0</difficult>
                <bndbox>
                        <xmin>191</xmin>
                        <ymin>510</ymin>
                        <xmax>270</xmax>
                        <ymax>548</ymax>
                </bndbox>
        </object>
 <object>
                <name>Ks</name>
                <pose>Unspecified</pose>
                <truncated>0</truncated>
                <difficult>0</difficult>
                <bndbox>
                        <xmin>197</xmin>
                        <ymin>461</ymin>
                        <xmax>287</xmax>
                        <ymax>503</ymax>
                </bndbox>
        </object>
 <object>
                <name>Ks</name>
                <pose>Unspecified</pose>
                <truncated>0</truncated>
                <difficult>0</difficult>
                <bndbox>
                        <xmin>341</xmin>
                        <ymin>353</ymin>
                        <xmax>432</xmax>
                        <ymax>396</ymax>
                </bndbox>
        </object>
</annotation>        
