<annotation>
        <folder>FOLDER</folder>
        <filename>950964829.jpg</filename>
        <path>data/scenes/train2\950964829.jpg</path>
        <source>
                <database>Unknown</database>
        </source>
        <size>
                <width>720</width>
                <height>720</height>
                <depth>3</depth>
        </size>
 <object>
                <name>4h</name>
                <pose>Unspecified</pose>
                <truncated>0</truncated>
                <difficult>0</difficult>
                <bndbox>
                        <xmin>163</xmin>
                        <ymin>368</ymin>
                        <xmax>286</xmax>
                        <ymax>415</ymax>
                </bndbox>
        </object>
 <object>
                <name>Tc</name>
                <pose>Unspecified</pose>
                <truncated>0</truncated>
                <difficult>0</difficult>
                <bndbox>
                        <xmin>178</xmin>
                        <ymin>306</ymin>
                        <xmax>301</xmax>
                        <ymax>374</ymax>
                </bndbox>
        </object>
 <object>
                <name>Qh</name>
                <pose>Unspecified</pose>
                <truncated>0</truncated>
                <difficult>0</difficult>
                <bndbox>
                        <xmin>221</xmin>
                        <ymin>219</ymin>
                        <xmax>334</xmax>
                        <ymax>294</ymax>
                </bndbox>
        </object>
 <object>
                <name>Qh</name>
                <pose>Unspecified</pose>
                <truncated>0</truncated>
                <difficult>0</difficult>
                <bndbox>
                        <xmin>504</xmin>
                        <ymin>171</ymin>
                        <xmax>609</xmax>
                        <ymax>245</ymax>
                </bndbox>
        </object>
</annotation>        
